celery_enqueue/__init__.py
celery_enqueue/cli.py
celery_enqueue/config.py
celery_enqueue/queue.py
celery_enqueue-1.0.1.dist-info/DESCRIPTION.rst
celery_enqueue-1.0.1.dist-info/METADATA
celery_enqueue-1.0.1.dist-info/RECORD
celery_enqueue-1.0.1.dist-info/WHEEL
celery_enqueue-1.0.1.dist-info/entry_points.txt
celery_enqueue-1.0.1.dist-info/metadata.json
celery_enqueue-1.0.1.dist-info/top_level.txt
