Metadata-Version: 2.0
Name: celery-enqueue
Version: 1.0.1
Summary: Command-line program to enqueue tasks within RabbitMQ for processing by Celery
Home-page: https://github.com/unchained-capital/celery-enqueue
Author: Dhruv Bansal
Author-email: dhruv@unchained-capital.com
License: MIT
Keywords: celery rabbitmq
Platform: UNKNOWN
Classifier: Development Status :: 3 - Alpha
Classifier: Intended Audience :: Developers
Classifier: Topic :: Utilities
Classifier: License :: OSI Approved :: MIT License
Classifier: Programming Language :: Python :: 2
Classifier: Programming Language :: Python :: 2.7
Classifier: Programming Language :: Python :: 3
Classifier: Programming Language :: Python :: 3.3
Classifier: Programming Language :: Python :: 3.4
Classifier: Programming Language :: Python :: 3.5
Classifier: Programming Language :: Python :: 3.6
Requires-Dist: PyYAML
Requires-Dist: celery (>=4)
